{
  "features": [
    {
      "geometry": {
        "coordinates": [
          14.311837,
          48.8048315
        ],
        "type": "Point"
      },
      "properties": {
        "_note": "<br><b>Poznámka:</b> Plešivec I - Za mostem 147, Český Krumlov <br><b>Adresa:</b> Plešivecká 147, Plešivec, 38101, Český Krumlov <p style='text-align: center'><u>Souřadnice převzaty z OSM!</u><br>Posunuto o 32.1 m",
        "amenity": "post_box",
        "collection_times": "Mo-Fr 14:45",
        "operator": "Česká pošta, s.p.",
        "ref": "37271:546"
      },
      "type": "Feature"
    },
    {
      "geometry": {
        "coordinates": [
          14.3113866,
          48.8016215
        ],
        "type": "Point"
      },
      "properties": {
        "_note": "<br><b>Poznámka:</b> Plešivec II/250,  pošta ČK 3, Český Krumlov <br><b>Adresa:</b> Sídliště Plešivec 250, Plešivec, 38101, Český Krumlov <p style='text-align: center'><u>Souřadnice převzaty z OSM!</u><br>Posunuto o 28.08 m",
        "amenity": "post_box",
        "collection_times": "Mo-Fr 16:30",
        "operator": "Česká pošta, s.p.",
        "ref": "37271:547"
      },
      "type": "Feature"
    },
    {
      "geometry": {
        "coordinates": [
          14.3116536,
          48.7971139
        ],
        "type": "Point"
      },
      "properties": {
        "_note": "<br><b>Poznámka:</b> Nové Spolí 49 <br><b>Adresa:</b> U Stromovky 49, Nové Spolí, 38101, Český Krumlov <p style='text-align: center'><u>Souřadnice převzaty z OSM!</u><br>Posunuto o 25.26 m",
        "amenity": "post_box",
        "collection_times": "Mo-Fr 08:00",
        "operator": "Česká pošta, s.p.",
        "ref": "37271:564"
      },
      "type": "Feature"
    },
    {
      "geometry": {
        "coordinates": [
          14.3126424,
          48.7983653
        ],
        "type": "Point"
      },
      "properties": {
        "_note": "<br><b>Poznámka:</b> Bar NON STOP, Nové Spolí 85 <br><b>Adresa:</b> Nové Spolí 85, 38101, Český Krumlov <p style='text-align: center'><u>Souřadnice převzaty z OSM!</u><br>Posunuto o 12.17 m",
        "amenity": "post_box",
        "collection_times": "Mo-Fr 08:00",
        "operator": "Česká pošta, s.p.",
        "ref": "37271:565"
      },
      "type": "Feature"
    },
    {
      "geometry": {
        "coordinates": [
          14.2514645,
          48.7980719
        ],
        "type": "Point"
      },
      "properties": {
        "_note": "<br><b>Poznámka:</b> Novosedly 11 <br><b>Adresa:</b> Novosedly 11, 38101, Kájov <p style='text-align: center'><u>Souřadnice převzaty z OSM!</u><br>Posunuto o 45.01 m",
        "amenity": "post_box",
        "collection_times": "Mo-Fr 08:00",
        "operator": "Česká pošta, s.p.",
        "ref": "37271:575"
      },
      "type": "Feature"
    },
    {
      "geometry": {
        "coordinates": [
          14.2416133,
          48.7855119
        ],
        "type": "Point"
      },
      "properties": {
        "_note": "<br><b>Poznámka:</b> Mezipotočí 33 <br><b>Adresa:</b> Mezipotočí 32, 38101, Kájov <p style='text-align: center'><u>Souřadnice převzaty z OSM!</u><br>Posunuto o 28.85 m",
        "amenity": "post_box",
        "collection_times": "Mo-Fr 08:00",
        "operator": "Česká pošta, s.p.",
        "ref": "37271:576"
      },
      "type": "Feature"
    },
    {
      "geometry": {
        "coordinates": [
          14.2903101,
          48.789011
        ],
        "type": "Point"
      },
      "properties": {
        "_note": "<br><b>Poznámka:</b> Větřní - Němče <br><b>Adresa:</b> Dolní Němče 18, Němče, 38101, Větřní <p style='text-align: center'><u>Souřadnice převzaty z OSM!</u><br>Posunuto o 66.62 m",
        "amenity": "post_box",
        "collection_times": "Mo-Fr 08:00",
        "operator": "Česká pošta, s.p.",
        "ref": "37271:588"
      },
      "type": "Feature"
    },
    {
      "geometry": {
        "coordinates": [
          14.2432153,
          48.7642039
        ],
        "type": "Point"
      },
      "properties": {
        "_note": "<br><b>Poznámka:</b> Slavkov 12 <br><b>Adresa:</b> Slavkov 12, 38101, Bohdalovice <p style='text-align: center'><u>Souřadnice převzaty z OSM!</u><br>Posunuto o 54.19 m",
        "amenity": "post_box",
        "collection_times": "Mo-Fr 08:00",
        "operator": "Česká pošta, s.p.",
        "ref": "37271:589"
      },
      "type": "Feature"
    },
    {
      "geometry": {
        "coordinates": [
          14.3084588,
          48.7648615
        ],
        "type": "Point"
      },
      "properties": {
        "_note": "<br><b>Poznámka:</b> Dobrné 9 <br><b>Adresa:</b> Dobrné 9, 38101, Větřní <p style='text-align: center'><u>Souřadnice převzaty z OSM!</u><br>Posunuto o 119.86 m",
        "amenity": "post_box",
        "collection_times": "Mo-Fr 08:00",
        "operator": "Česká pošta, s.p.",
        "ref": "37271:593"
      },
      "type": "Feature"
    },
    {
      "geometry": {
        "coordinates": [
          14.289631,
          48.775565
        ],
        "type": "Point"
      },
      "properties": {
        "_note": "<br><b>Poznámka:</b> Budova pošty Větřní <br><b>Adresa:</b> Šumavská 1, 38211, Větřní <p style='text-align: center'><u>Souřadnice převzaty z OSM!</u><br>Posunuto o 19.72 m",
        "amenity": "post_box",
        "collection_times": "Mo-Fr 08:00",
        "operator": "Česká pošta, s.p.",
        "ref": "37271:601"
      },
      "type": "Feature"
    },
    {
      "geometry": {
        "coordinates": [
          14.2979879,
          48.7790453
        ],
        "type": "Point"
      },
      "properties": {
        "_note": "<br><b>Poznámka:</b> Větřní č.82 <br><b>Adresa:</b> Šumavská 82, 38211, Větřní <p style='text-align: center'><u>Souřadnice převzaty z OSM!</u><br>Posunuto o 6.92 m",
        "amenity": "post_box",
        "collection_times": "Mo-Fr 08:00",
        "operator": "Česká pošta, s.p.",
        "ref": "37271:602"
      },
      "type": "Feature"
    },
    {
      "geometry": {
        "coordinates": [
          14.288558,
          48.776968
        ],
        "type": "Point"
      },
      "properties": {
        "_note": "<br><b>Poznámka:</b> Větřní 199 <br><b>Adresa:</b> Na Žofíně 199, 38211, Větřní <p style='text-align: center'><u>Souřadnice převzaty z OSM!</u><br>Posunuto o 32.44 m",
        "amenity": "post_box",
        "collection_times": "Mo-Fr 08:00",
        "operator": "Česká pošta, s.p.",
        "ref": "37271:603"
      },
      "type": "Feature"
    },
    {
      "geometry": {
        "coordinates": [
          14.2870817,
          48.7765975
        ],
        "type": "Point"
      },
      "properties": {
        "_note": "<br><b>Poznámka:</b> Větřní 301 <br><b>Adresa:</b> Sadová 301, 38211, Větřní <p style='text-align: center'><u>Souřadnice převzaty z OSM!</u><br>Posunuto o 31.07 m",
        "amenity": "post_box",
        "collection_times": "Mo-Fr 08:00",
        "operator": "Česká pošta, s.p.",
        "ref": "37271:604"
      },
      "type": "Feature"
    },
    {
      "geometry": {
        "coordinates": [
          14.2868059,
          48.7816145
        ],
        "type": "Point"
      },
      "properties": {
        "_note": "<br><b>Poznámka:</b> Větřní - Němče 3 <br><b>Adresa:</b> U Studánky 3, Němče, 38211, Větřní <p style='text-align: center'><u>Souřadnice převzaty z OSM!</u><br>Posunuto o 16.41 m",
        "amenity": "post_box",
        "collection_times": "Mo-Fr 08:00",
        "operator": "Česká pošta, s.p.",
        "ref": "37271:605"
      },
      "type": "Feature"
    }
  ],
  "type": "FeatureCollection"
}