{
  "features": [
    {
      "geometry": {
        "coordinates": [
          14.4538857,
          51.001102
        ],
        "type": "Point"
      },
      "properties": {
        "_note": "<br><b>Poznámka:</b>  <br><b>Adresa:</b> Křečanská 630, 40777, Šluknov ",
        "amenity": "post_box",
        "collection_times": "Mo-Fr 09:00",
        "operator": "Česká pošta, s.p.",
        "ref": "40371:293"
      },
      "type": "Feature"
    },
    {
      "geometry": {
        "coordinates": [
          14.4890332,
          50.9986219
        ],
        "type": "Point"
      },
      "properties": {
        "_note": "<br><b>Poznámka:</b> u č.p. 324 <br><b>Adresa:</b> Děčín; Šluknov; Království <p style='color:red; text-align:center'><b>POZOR:</b> Souřadnice jsou pouze <u>orientační</u>!<br>Přesné umístění nutno dohledat dle poznámky!</p>",
        "amenity": "post_box",
        "collection_times": "Mo-Fr 09:00",
        "operator": "Česká pošta, s.p.",
        "ref": "40371:311"
      },
      "type": "Feature"
    },
    {
      "geometry": {
        "coordinates": [
          14.4619764,
          51.0025522
        ],
        "type": "Point"
      },
      "properties": {
        "_note": "<br><b>Poznámka:</b>  <br><b>Adresa:</b> Sídliště 990, 40777, Šluknov ",
        "amenity": "post_box",
        "collection_times": "Mo-Fr 09:00",
        "operator": "Česká pošta, s.p.",
        "ref": "40371:345"
      },
      "type": "Feature"
    },
    {
      "geometry": {
        "coordinates": [
          14.4539078,
          51.0032773
        ],
        "type": "Point"
      },
      "properties": {
        "_note": "<br><b>Poznámka:</b> pošta Šluknov <br><b>Adresa:</b> Karlova 322, 40777, Šluknov ",
        "amenity": "post_box",
        "collection_times": "Mo-Fr 09:00",
        "operator": "Česká pošta, s.p.",
        "ref": "40371:356"
      },
      "type": "Feature"
    },
    {
      "geometry": {
        "coordinates": [
          14.4598653,
          51.0059419
        ],
        "type": "Point"
      },
      "properties": {
        "_note": "<br><b>Poznámka:</b>  <br><b>Adresa:</b> Lužická 1093, 40777, Šluknov ",
        "amenity": "post_box",
        "collection_times": "Mo-Fr 09:00",
        "operator": "Česká pošta, s.p.",
        "ref": "40371:363"
      },
      "type": "Feature"
    }
  ],
  "type": "FeatureCollection"
}