{
  "features": [
    {
      "geometry": {
        "coordinates": [
          14.4762179,
          50.4748316
        ],
        "type": "Point"
      },
      "properties": {
        "_note": "<br><b>Poznámka:</b>  <br><b>Adresa:</b> Chudolazy 1, 27721, Medonosy ",
        "amenity": "post_box",
        "collection_times": "Mo-Fr 08:00",
        "operator": "Česká pošta, s.p.",
        "operator:wikidata": "Q341090",
        "ref": "27600:47"
      },
      "type": "Feature"
    },
    {
      "geometry": {
        "coordinates": [
          14.4872137,
          50.4939685
        ],
        "type": "Point"
      },
      "properties": {
        "_note": "<br><b>Poznámka:</b>  <br><b>Adresa:</b> č.p. 32, 27721, Medonosy ",
        "amenity": "post_box",
        "collection_times": "Mo-Fr 08:00",
        "operator": "Česká pošta, s.p.",
        "operator:wikidata": "Q341090",
        "ref": "27600:48"
      },
      "type": "Feature"
    },
    {
      "geometry": {
        "coordinates": [
          14.500528,
          50.4827728
        ],
        "type": "Point"
      },
      "properties": {
        "_note": "<br><b>Poznámka:</b>  <br><b>Adresa:</b> Nové Osinalice 5, 27721, Medonosy ",
        "amenity": "post_box",
        "collection_times": "Mo-Fr 08:00",
        "operator": "Česká pošta, s.p.",
        "operator:wikidata": "Q341090",
        "ref": "27600:52"
      },
      "type": "Feature"
    },
    {
      "geometry": {
        "coordinates": [
          14.4449039,
          50.477694
        ],
        "type": "Point"
      },
      "properties": {
        "_note": "<br><b>Poznámka:</b>  <br><b>Adresa:</b> Brocno 27, 41108, Štětí ",
        "amenity": "post_box",
        "collection_times": "Mo-Fr 08:00",
        "operator": "Česká pošta, s.p.",
        "operator:wikidata": "Q341090",
        "ref": "41300:17"
      },
      "type": "Feature"
    },
    {
      "geometry": {
        "coordinates": [
          14.4410673,
          50.4917554
        ],
        "type": "Point"
      },
      "properties": {
        "_note": "<br><b>Poznámka:</b>  <br><b>Adresa:</b> Veselí 18, 41108, Štětí ",
        "amenity": "post_box",
        "collection_times": "Mo-Fr 08:00",
        "operator": "Česká pošta, s.p.",
        "operator:wikidata": "Q341090",
        "ref": "41300:18"
      },
      "type": "Feature"
    },
    {
      "geometry": {
        "coordinates": [
          14.4384474,
          50.500308
        ],
        "type": "Point"
      },
      "properties": {
        "_note": "<br><b>Poznámka:</b>  <br><b>Adresa:</b> Újezd 4, 41108, Štětí ",
        "amenity": "post_box",
        "collection_times": "Mo-Fr 08:00",
        "operator": "Česká pošta, s.p.",
        "operator:wikidata": "Q341090",
        "ref": "41300:19"
      },
      "type": "Feature"
    },
    {
      "geometry": {
        "coordinates": [
          14.4148229,
          50.5091747
        ],
        "type": "Point"
      },
      "properties": {
        "_note": "<br><b>Poznámka:</b> Lomy <br><b>Adresa:</b> Strachaly 39, 41108, Snědovice ",
        "amenity": "post_box",
        "collection_times": "Mo-Fr 08:00",
        "operator": "Česká pošta, s.p.",
        "operator:wikidata": "Q341090",
        "ref": "41300:21"
      },
      "type": "Feature"
    },
    {
      "geometry": {
        "coordinates": [
          14.4248158,
          50.5130947
        ],
        "type": "Point"
      },
      "properties": {
        "_note": "<br><b>Poznámka:</b> zastávka <br><b>Adresa:</b> Strachaly 35, 41108, Snědovice ",
        "amenity": "post_box",
        "collection_times": "Mo-Fr 08:00",
        "operator": "Česká pošta, s.p.",
        "operator:wikidata": "Q341090",
        "ref": "41300:22"
      },
      "type": "Feature"
    },
    {
      "geometry": {
        "coordinates": [
          14.4761391,
          50.5122414
        ],
        "type": "Point"
      },
      "properties": {
        "_note": "<br><b>Poznámka:</b>  <br><b>Adresa:</b> Bylochov 19, 41108, Snědovice ",
        "amenity": "post_box",
        "collection_times": "Mo-Fr 08:00",
        "operator": "Česká pošta, s.p.",
        "operator:wikidata": "Q341090",
        "ref": "41300:23"
      },
      "type": "Feature"
    },
    {
      "geometry": {
        "coordinates": [
          14.426765,
          50.4830582
        ],
        "type": "Point"
      },
      "properties": {
        "_note": "<br><b>Poznámka:</b>  <br><b>Adresa:</b> Chcebuz 55, 41173, Štětí ",
        "amenity": "post_box",
        "collection_times": "Mo-Fr 08:00",
        "operator": "Česká pošta, s.p.",
        "operator:wikidata": "Q341090",
        "ref": "41300:95"
      },
      "type": "Feature"
    },
    {
      "geometry": {
        "coordinates": [
          14.4884524,
          50.5078819
        ],
        "type": "Point"
      },
      "properties": {
        "_note": "<br><b>Poznámka:</b> U hasičské kapličky, Bukovec <br><b>Adresa:</b> Bukovec 13, 47201, Dubá <p style='text-align: center'><u>Souřadnice převzaty z OSM!</u><br>Posunuto o 25.84 m",
        "amenity": "post_box",
        "collection_times": "Mo-Fr 08:00",
        "operator": "Česká pošta, s.p.",
        "operator:wikidata": "Q341090",
        "ref": "47007:153"
      },
      "type": "Feature"
    }
  ],
  "type": "FeatureCollection"
}