{
  "features": [
    {
      "geometry": {
        "coordinates": [
          14.4969967,
          50.5762654
        ],
        "type": "Point"
      },
      "properties": {
        "_note": "<br><b>Poznámka:</b> V obci, Dřevčice - u obchodu č.p.1 <br><b>Adresa:</b> Dřevčice 1, 47201, Dubá <p style='text-align: center'><u>Souřadnice převzaty z OSM!</u><br>Posunuto o 11.22 m",
        "amenity": "post_box",
        "collection_times": "Mo-Fr 08:00",
        "operator": "Česká pošta, s.p.",
        "ref": "47007:140"
      },
      "type": "Feature"
    },
    {
      "geometry": {
        "coordinates": [
          14.4790985,
          50.5841361
        ],
        "type": "Point"
      },
      "properties": {
        "_note": "<br><b>Poznámka:</b> V obci, Heřmánky - u kapličky <br><b>Adresa:</b> Heřmánky 15, 47201, Dubá <p style='text-align: center'><u>Souřadnice převzaty z OSM!</u><br>Posunuto o 46.94 m",
        "amenity": "post_box",
        "collection_times": "Mo-Fr 08:00",
        "operator": "Česká pošta, s.p.",
        "ref": "47007:141"
      },
      "type": "Feature"
    },
    {
      "geometry": {
        "coordinates": [
          14.4142181,
          50.5868756
        ],
        "type": "Point"
      },
      "properties": {
        "_note": "<br><b>Poznámka:</b> U obchodu, čp.15,  Skalka <br><b>Adresa:</b> Skalka 15, 47002, Blíževedly <p style='text-align: center'><u>Souřadnice převzaty z OSM!</u><br>Posunuto o 7.26 m",
        "amenity": "post_box",
        "collection_times": "Mo-Fr 08:00",
        "operator": "Česká pošta, s.p.",
        "ref": "47007:41"
      },
      "type": "Feature"
    },
    {
      "geometry": {
        "coordinates": [
          14.4925967,
          50.6174384
        ],
        "type": "Point"
      },
      "properties": {
        "_note": "<br><b>Poznámka:</b> na budově knihovny, čp.12, Holany <br><b>Adresa:</b> č.p. 12, 47002, Holany <p style='text-align: center'><u>Souřadnice převzaty z OSM!</u><br>Posunuto o 11.36 m",
        "amenity": "post_box",
        "collection_times": "Mo-Fr 08:00",
        "operator": "Česká pošta, s.p.",
        "ref": "47007:52"
      },
      "type": "Feature"
    },
    {
      "geometry": {
        "coordinates": [
          14.4867216,
          50.5936647
        ],
        "type": "Point"
      },
      "properties": {
        "_note": "<br><b>Poznámka:</b> Zastávka, u čp.30, Loubí <br><b>Adresa:</b> Loubí 30, 47002, Holany <p style='text-align: center'><u>Souřadnice převzaty z OSM!</u><br>Posunuto o 24.06 m",
        "amenity": "post_box",
        "collection_times": "Mo-Fr 08:00",
        "operator": "Česká pošta, s.p.",
        "ref": "47007:55"
      },
      "type": "Feature"
    },
    {
      "geometry": {
        "coordinates": [
          14.4382297,
          50.6130235
        ],
        "type": "Point"
      },
      "properties": {
        "_note": "<br><b>Poznámka:</b> Zastávka, u čp.16, Litice <br><b>Adresa:</b> Litice 16, 47002, Blíževedly <p style='text-align: center'><u>Souřadnice převzaty z OSM!</u><br>Posunuto o 0.0 cm",
        "amenity": "post_box",
        "collection_times": "Mo-Fr 08:00",
        "operator": "Česká pošta, s.p.",
        "ref": "47007:57"
      },
      "type": "Feature"
    }
  ],
  "type": "FeatureCollection"
}