{
  "features": [
    {
      "geometry": {
        "coordinates": [
          15.0438824,
          49.103233
        ],
        "type": "Point"
      },
      "properties": {
        "_note": "<br><b>Poznámka:</b> budova pošty, Horní Pěna <br><b>Adresa:</b> č.p. 96, 37831, Horní Pěna ",
        "amenity": "post_box",
        "collection_times": "Mo-Fr 08:00",
        "operator": "Česká pošta, s.p.",
        "ref": "37702:23"
      },
      "type": "Feature"
    },
    {
      "geometry": {
        "coordinates": [
          15.0320328,
          49.1442661
        ],
        "type": "Point"
      },
      "properties": {
        "_note": "<br><b>Poznámka:</b> Otín-domov důchodců <br><b>Adresa:</b> Otín 103, 37701, Jindřichův Hradec ",
        "amenity": "post_box",
        "collection_times": "Mo-Fr 08:00",
        "operator": "Česká pošta, s.p.",
        "ref": "37702:288"
      },
      "type": "Feature"
    },
    {
      "geometry": {
        "coordinates": [
          15.0349725,
          49.1444841
        ],
        "type": "Point"
      },
      "properties": {
        "_note": "<br><b>Poznámka:</b> Jitka <br><b>Adresa:</b> Otín 3, 37701, Jindřichův Hradec <p style='text-align: center'><u>Souřadnice převzaty z OSM!</u><br>Posunuto o 0.0 cm",
        "amenity": "post_box",
        "collection_times": "Mo-Fr 08:00",
        "operator": "Česká pošta, s.p.",
        "ref": "37702:39"
      },
      "type": "Feature"
    },
    {
      "geometry": {
        "coordinates": [
          15.0394532,
          49.1475728
        ],
        "type": "Point"
      },
      "properties": {
        "_note": "<br><b>Poznámka:</b> Otín Boubelovka, Jindřichův Hradec <br><b>Adresa:</b> Otín 89, 37701, Jindřichův Hradec <p style='text-align: center'><u>Souřadnice převzaty z OSM!</u><br>Posunuto o 18.39 m",
        "amenity": "post_box",
        "collection_times": "Mo-Fr 08:00",
        "operator": "Česká pošta, s.p.",
        "ref": "37702:40"
      },
      "type": "Feature"
    },
    {
      "geometry": {
        "coordinates": [
          15.0616339,
          49.1489088
        ],
        "type": "Point"
      },
      "properties": {
        "_note": "<br><b>Poznámka:</b> Jindřiš <br><b>Adresa:</b> Jindřiš 48, 37701, Rodvínov ",
        "amenity": "post_box",
        "collection_times": "Mo-Fr 08:00",
        "operator": "Česká pošta, s.p.",
        "ref": "37702:41"
      },
      "type": "Feature"
    },
    {
      "geometry": {
        "coordinates": [
          15.0597337,
          49.1184924
        ],
        "type": "Point"
      },
      "properties": {
        "_note": "<br><b>Poznámka:</b> Hrudkov <br><b>Adresa:</b> Hrutkov 9, 37701, Hospříz ",
        "amenity": "post_box",
        "collection_times": "Mo-Fr 09:00",
        "operator": "Česká pošta, s.p.",
        "ref": "37702:50"
      },
      "type": "Feature"
    },
    {
      "geometry": {
        "coordinates": [
          15.0767585,
          49.108941
        ],
        "type": "Point"
      },
      "properties": {
        "_note": "<br><b>Poznámka:</b> Kačlehy <br><b>Adresa:</b> č.p. 42, 37701, Kačlehy ",
        "amenity": "post_box",
        "collection_times": "Mo-Fr 09:30",
        "operator": "Česká pošta, s.p.",
        "ref": "37702:51"
      },
      "type": "Feature"
    },
    {
      "geometry": {
        "coordinates": [
          15.0846313,
          49.1288526
        ],
        "type": "Point"
      },
      "properties": {
        "_note": "<br><b>Poznámka:</b> Hozpříz <br><b>Adresa:</b> č.p. 28, 37701, Hospříz ",
        "amenity": "post_box",
        "collection_times": "Mo-Fr 10:00",
        "operator": "Česká pošta, s.p.",
        "ref": "37702:52"
      },
      "type": "Feature"
    },
    {
      "geometry": {
        "coordinates": [
          15.0964357,
          49.1420439
        ],
        "type": "Point"
      },
      "properties": {
        "_note": "<br><b>Poznámka:</b> budova pošty, Blažejov <br><b>Adresa:</b> č.p. 15, 37852, Blažejov <p style='text-align: center'><u>Souřadnice převzaty z OSM!</u><br>Posunuto o 14.71 m",
        "amenity": "post_box",
        "collection_times": "Mo-Fr 10:00",
        "operator": "Česká pošta, s.p.",
        "ref": "37702:53"
      },
      "type": "Feature"
    },
    {
      "geometry": {
        "coordinates": [
          15.1010701,
          49.1490271
        ],
        "type": "Point"
      },
      "properties": {
        "_note": "<br><b>Poznámka:</b> Dvoreček <br><b>Adresa:</b> Dvoreček 12, 37701, Blažejov ",
        "amenity": "post_box",
        "collection_times": "Mo-Fr 11:30",
        "operator": "Česká pošta, s.p.",
        "ref": "37702:57"
      },
      "type": "Feature"
    },
    {
      "geometry": {
        "coordinates": [
          15.0424749,
          49.1371955
        ],
        "type": "Point"
      },
      "properties": {
        "_note": "<br><b>Poznámka:</b> Otín <br><b>Adresa:</b> Otín 91, 37701, Jindřichův Hradec ",
        "amenity": "post_box",
        "collection_times": "Mo-Fr 08:00",
        "operator": "Česká pošta, s.p.",
        "ref": "37702:58"
      },
      "type": "Feature"
    }
  ],
  "type": "FeatureCollection"
}