{
  "features": [
    {
      "geometry": {
        "coordinates": [
          15.5382407,
          50.3153015
        ],
        "type": "Point"
      },
      "properties": {
        "_note": "<br><b>Poznámka:</b> Šaplava - stojam u prodejny, č.p. 51 <br><b>Adresa:</b> č.p. 51, 50353, Šaplava <p style='text-align: center'><u>Souřadnice převzaty z OSM!</u><br>Posunuto o 16.96 m",
        "amenity": "post_box",
        "collection_times": "Mo-Fr 08:00",
        "operator": "Česká pošta, s.p.",
        "ref": "50370:435"
      },
      "type": "Feature"
    },
    {
      "geometry": {
        "coordinates": [
          15.4717414,
          50.3095503
        ],
        "type": "Point"
      },
      "properties": {
        "_note": "<br><b>Poznámka:</b> Chotělice, pohostinství Zelený háj, č.p. 75 <br><b>Adresa:</b> Chotělice 75, 50353, Smidary <p style='text-align: center'><u>Souřadnice převzaty z OSM!</u><br>Posunuto o 9.61 m",
        "amenity": "post_box",
        "collection_times": "Mo-Fr 08:00",
        "operator": "Česká pošta, s.p.",
        "ref": "50370:436"
      },
      "type": "Feature"
    },
    {
      "geometry": {
        "coordinates": [
          15.5123557,
          50.3299371
        ],
        "type": "Point"
      },
      "properties": {
        "_note": "<br><b>Poznámka:</b> Pošta Ohnišťany <br><b>Adresa:</b> č.p. 91, 50354, Ohnišťany <p style='text-align: center'><u>Souřadnice převzaty z OSM!</u><br>Posunuto o 5.82 m",
        "amenity": "post_box",
        "collection_times": "Mo-Fr 08:00",
        "operator": "Česká pošta, s.p.",
        "ref": "50370:439"
      },
      "type": "Feature"
    },
    {
      "geometry": {
        "coordinates": [
          15.4778245,
          50.2924275
        ],
        "type": "Point"
      },
      "properties": {
        "_note": "<br><b>Poznámka:</b> OÚ, Smidary <br><b>Adresa:</b> Náměstí Prof. Babáka 106, 50353, Smidary <p style='text-align: center'><u>Souřadnice převzaty z OSM!</u><br>Posunuto o 17.7 m",
        "amenity": "post_box",
        "collection_times": "Mo-Fr 08:00",
        "operator": "Česká pošta, s.p.",
        "ref": "50370:443"
      },
      "type": "Feature"
    },
    {
      "geometry": {
        "coordinates": [
          15.4798948,
          50.2927723
        ],
        "type": "Point"
      },
      "properties": {
        "_note": "<br><b>Poznámka:</b> pošta Smidary <br><b>Adresa:</b> Poštovní 2, 50353, Smidary <p style='text-align: center'><u>Souřadnice převzaty z OSM!</u><br>Posunuto o 7.39 m",
        "amenity": "post_box",
        "collection_times": "Mo-Fr 08:00",
        "operator": "Česká pošta, s.p.",
        "ref": "50370:456"
      },
      "type": "Feature"
    },
    {
      "geometry": {
        "coordinates": [
          15.494462,
          50.3376373
        ],
        "type": "Point"
      },
      "properties": {
        "_note": "<br><b>Poznámka:</b> prodejna Staré Smrkovice <br><b>Adresa:</b> č.p. 19, 50801, Staré Smrkovice <p style='text-align: center'><u>Souřadnice převzaty z OSM!</u><br>Posunuto o 17.25 m",
        "amenity": "post_box",
        "collection_times": "Mo-Fr 08:00",
        "operator": "Česká pošta, s.p.",
        "ref": "50770:286"
      },
      "type": "Feature"
    },
    {
      "geometry": {
        "coordinates": [
          15.5285038,
          50.3406915
        ],
        "type": "Point"
      },
      "properties": {
        "_note": "<br><b>Poznámka:</b> prodejna Tereziny Dary <br><b>Adresa:</b> Tereziny Dary 18, 50801, Lískovice <p style='text-align: center'><u>Souřadnice převzaty z OSM!</u><br>Posunuto o 32.05 m",
        "amenity": "post_box",
        "collection_times": "Mo-Fr 08:00",
        "operator": "Česká pošta, s.p.",
        "ref": "50770:287"
      },
      "type": "Feature"
    },
    {
      "geometry": {
        "coordinates": [
          15.5543429,
          50.3365095
        ],
        "type": "Point"
      },
      "properties": {
        "_note": "<br><b>Poznámka:</b> Lískovice  u obecní knihovny <br><b>Adresa:</b> č.p. 72, 50801, Lískovice <p style='text-align: center'><u>Souřadnice převzaty z OSM!</u><br>Posunuto o 4.68 m",
        "amenity": "post_box",
        "collection_times": "Mo-Fr 08:00",
        "operator": "Česká pošta, s.p.",
        "ref": "50770:292"
      },
      "type": "Feature"
    }
  ],
  "type": "FeatureCollection"
}