{
  "features": [
    {
      "geometry": {
        "coordinates": [
          16.258066,
          49.2549777
        ],
        "type": "Point"
      },
      "properties": {
        "_note": "<br><b>Poznámka:</b> čekárna, Ludvíkov <br><b>Adresa:</b> Ludvíkov 1, 59501, Velká Bíteš ",
        "amenity": "post_box",
        "collection_times": "Mo-Fr 08:50",
        "operator": "Česká pošta, s.p.",
        "ref": "59502:3"
      },
      "type": "Feature"
    },
    {
      "geometry": {
        "coordinates": [
          16.2008074,
          49.2661702
        ],
        "type": "Point"
      },
      "properties": {
        "_note": "<br><b>Poznámka:</b> kulturní dům, Jindřichov <br><b>Adresa:</b> Jindřichov 12, 59501, Velká Bíteš ",
        "amenity": "post_box",
        "collection_times": "Mo-Fr 09:15",
        "operator": "Česká pošta, s.p.",
        "ref": "59502:4"
      },
      "type": "Feature"
    },
    {
      "geometry": {
        "coordinates": [
          16.254085,
          49.2223835
        ],
        "type": "Point"
      },
      "properties": {
        "_note": "<br><b>Poznámka:</b> Potraviny <br><b>Adresa:</b> č.p. 109, 66484, Újezd u Rosic <p style='text-align: center'><u>Souřadnice převzaty z OSM!</u><br>Posunuto o 8.27 m",
        "amenity": "post_box",
        "collection_times": "Mo-Fr 10:00",
        "operator": "Česká pošta, s.p.",
        "ref": "60010:167"
      },
      "type": "Feature"
    },
    {
      "geometry": {
        "coordinates": [
          16.2558181,
          49.2404198
        ],
        "type": "Point"
      },
      "properties": {
        "_note": "<br><b>Poznámka:</b> Potraviny <br><b>Adresa:</b> č.p. 117, 66484, Stanoviště <p style='text-align: center'><u>Souřadnice převzaty z OSM!</u><br>Posunuto o 10.64 m",
        "amenity": "post_box",
        "collection_times": "Mo-Fr 11:00",
        "operator": "Česká pošta, s.p.",
        "ref": "60010:168"
      },
      "type": "Feature"
    },
    {
      "geometry": {
        "coordinates": [
          16.1941621,
          49.2308377
        ],
        "type": "Point"
      },
      "properties": {
        "_note": "<br><b>Poznámka:</b>  <br><b>Adresa:</b> č.p. 31, 67571, Jinošov ",
        "amenity": "post_box",
        "collection_times": "Mo-Fr 08:10",
        "operator": "Česká pošta, s.p.",
        "ref": "67407:247"
      },
      "type": "Feature"
    },
    {
      "geometry": {
        "coordinates": [
          16.1747287,
          49.2463321
        ],
        "type": "Point"
      },
      "properties": {
        "_note": "<br><b>Poznámka:</b> pod silničním zrcadlem <br><b>Adresa:</b> č.p. 20, 67571, Pucov <p style='text-align: center'><u>Souřadnice převzaty z OSM!</u><br>Posunuto o 18.11 m",
        "amenity": "post_box",
        "collection_times": "Mo-Fr 08:20",
        "operator": "Česká pošta, s.p.",
        "ref": "67407:248"
      },
      "type": "Feature"
    },
    {
      "geometry": {
        "coordinates": [
          16.2324897,
          49.2444721
        ],
        "type": "Point"
      },
      "properties": {
        "_note": "<br><b>Poznámka:</b>  <br><b>Adresa:</b> č.p. 19, 67571, Krokočín ",
        "amenity": "post_box",
        "collection_times": "Mo-Fr 09:30",
        "operator": "Česká pošta, s.p.",
        "ref": "67407:250"
      },
      "type": "Feature"
    },
    {
      "geometry": {
        "coordinates": [
          16.2275071,
          49.2256291
        ],
        "type": "Point"
      },
      "properties": {
        "_note": "<br><b>Poznámka:</b>  <br><b>Adresa:</b> č.p. 36, 67571, Hluboké ",
        "amenity": "post_box",
        "collection_times": "Mo-Fr 10:00",
        "operator": "Česká pošta, s.p.",
        "ref": "67407:251"
      },
      "type": "Feature"
    },
    {
      "geometry": {
        "coordinates": [
          16.1879954,
          49.2140616
        ],
        "type": "Point"
      },
      "properties": {
        "_note": "<br><b>Poznámka:</b>  <br><b>Adresa:</b> Otradice 9, 67571, Náměšť nad Oslavou ",
        "amenity": "post_box",
        "collection_times": "Mo-Fr 11:30",
        "operator": "Česká pošta, s.p.",
        "ref": "67407:252"
      },
      "type": "Feature"
    }
  ],
  "type": "FeatureCollection"
}