{
  "features": [
    {
      "geometry": {
        "coordinates": [
          16.9858522,
          50.3324817
        ],
        "type": "Point"
      },
      "properties": {
        "_note": "<br><b>Poznámka:</b> Uhelná, Nové Vilémovice 71 (stojan) <br><b>Adresa:</b> Nové Vilémovice 71, 79070, Uhelná ",
        "amenity": "post_box",
        "collection_times": "Mo-Fr 11:45",
        "operator": "Česká pošta, s.p.",
        "ref": "79007:106"
      },
      "type": "Feature"
    },
    {
      "geometry": {
        "coordinates": [
          17.047785,
          50.3109214
        ],
        "type": "Point"
      },
      "properties": {
        "_note": "<br><b>Poznámka:</b> Skorošice, Petrovice 230, aut.zastávka (stojan) <br><b>Adresa:</b> Jeseník; Skorošice; Petrovice <p style='color:red; text-align:center'><b>POZOR:</b> Souřadnice jsou pouze <u>orientační</u>!<br>Přesné umístění nutno dohledat dle poznámky!</p>",
        "amenity": "post_box",
        "collection_times": "Mo-Fr 11:15",
        "operator": "Česká pošta, s.p.",
        "ref": "79007:43"
      },
      "type": "Feature"
    },
    {
      "geometry": {
        "coordinates": [
          17.0457348,
          50.3452552
        ],
        "type": "Point"
      },
      "properties": {
        "_note": "<br><b>Poznámka:</b> Partner Vlčice u Jeseníku 95  (stojan) <br><b>Adresa:</b> č.p. 95, 79065, Vlčice ",
        "amenity": "post_box",
        "collection_times": "Mo-Fr 10:30",
        "operator": "Česká pošta, s.p.",
        "ref": "79007:62"
      },
      "type": "Feature"
    }
  ],
  "type": "FeatureCollection"
}